kerttula/__init__.py
kerttula/kerttula.py
kerttula/py.typed
kerttula-0.1.24.dist-info/licenses/LICENSE.rst
kerttula-0.1.24.dist-info/METADATA
kerttula-0.1.24.dist-info/WHEEL
kerttula-0.1.24.dist-info/entry_points.txt
kerttula-0.1.24.dist-info/top_level.txt
kerttula-0.1.24.dist-info/RECORD
