Metadata-Version: 2.4
Name: kerttula
Version: 0.1.24
Summary: Juha's home automation application
Author-email: J Meskanen <juham.api@gmail.com>
Maintainer-email: "J. Meskanen" <juham.api@gmail.com>
License-Expression: MIT
Project-URL: Homepage, https://gitlab.com/juham/kerttula
Project-URL: Bug Reports, https://gitlab.com/juham/kerttula
Project-URL: Funding, https://meskanen.com
Project-URL: Say Thanks!, http://meskanen.com
Project-URL: Source, https://gitlab.com/juham/kerttula
Keywords: home,automation,juham,masterpiece
Classifier: Development Status :: 4 - Beta
Classifier: Intended Audience :: Developers
Classifier: Topic :: Software Development
Classifier: Programming Language :: Python :: 3.8
Requires-Python: >=3.8
License-File: LICENSE.rst
Requires-Dist: juham-automation>=0.2.11
Requires-Dist: juham-visualcrossing>=0.1.10
Requires-Dist: juham-openweathermap>=0.1.11
Requires-Dist: juham-systemstatus>=0.1.14
Requires-Dist: juham-watermeter>=0.1.6
Requires-Dist: juham-shelly>=0.1.16
Requires-Dist: juham-homewizard>=0.1.0
Requires-Dist: juham-spothintafi>=0.1.3
Requires-Dist: importlib-metadata
Provides-Extra: dev
Requires-Dist: check-manifest; extra == "dev"
Dynamic: license-file
